pastebin_uploader/__init__.py
pastebin_uploader/pastebin.py
pastebin_uploader_SockYeh-1.0.0.dist-info/LICENSE
pastebin_uploader_SockYeh-1.0.0.dist-info/METADATA
pastebin_uploader_SockYeh-1.0.0.dist-info/WHEEL
pastebin_uploader_SockYeh-1.0.0.dist-info/top_level.txt
pastebin_uploader_SockYeh-1.0.0.dist-info/RECORD
