Metadata-Version: 2.1
Name: pastebin-uploader-SockYeh
Version: 1.0.0
Summary: This is a pastebin uploader with alot of features.
Home-page: https://github.com/SockYeh/Pastebin-Uplaoder
Author: SockYeh
Author-email: author@example.com
License: UNKNOWN
Project-URL: Bug Tracker, https://github.com/SockYeh/Pastebin-Uplaoder/issues
Platform: UNKNOWN
Classifier: Programming Language :: Python :: 3
Classifier: License :: OSI Approved :: MIT License
Classifier: Operating System :: OS Independent
Requires-Python: >=3.6
License-File: LICENSE
